fastxpy/__init__.py
fastxpy/fasta.py
fastxpy-1.0.0a8.dist-info/DESCRIPTION.rst
fastxpy-1.0.0a8.dist-info/METADATA
fastxpy-1.0.0a8.dist-info/RECORD
fastxpy-1.0.0a8.dist-info/WHEEL
fastxpy-1.0.0a8.dist-info/metadata.json
fastxpy-1.0.0a8.dist-info/top_level.txt
