Metadata-Version: 2.0
Name: fastxpy
Version: 1.0.0a8
Summary: fasta and fastq file functions
Home-page: https://github.com/mustafa-guler/fastxpy
Author: Mustafa Guler
Author-email: mguler@ucsd.edu
License: UNKNOWN
Platform: UNKNOWN
